src/__init__.py
src/anti.py
src/setup.py
anti_theunsocialengineer-0.0.2.dist-info/METADATA
anti_theunsocialengineer-0.0.2.dist-info/WHEEL
anti_theunsocialengineer-0.0.2.dist-info/licenses/LICENSE
anti_theunsocialengineer-0.0.2.dist-info/RECORD
