Metadata-Version: 2.1
Name: Anti_TheUnsocialEngineer
Version: 0.0.2
Summary: A package to create bots on Antiland.com
Project-URL: Homepage, https://github.com/TheUnsocialEngineer/Anti.py
Project-URL: Bug Tracker, https://github.com/TheUnsocialEngineer/Anti.py/issues
Author-email: TheUnsocialEngineer <TheUnsocialEngineer@protonmail.com>
License-File: LICENSE
Classifier: License :: OSI Approved :: MIT License
Classifier: Operating System :: OS Independent
Classifier: Programming Language :: Python :: 3
Requires-Python: >=3.7
